dssketch/__init__.py
dssketch/api.py
dssketch/cli.py
dssketch/config.py
dssketch/data_cli.py
dssketch/converters/__init__.py
dssketch/converters/designspace_to_dss.py
dssketch/converters/dss_to_designspace.py
dssketch/core/__init__.py
dssketch/core/instances.py
dssketch/core/mappings.py
dssketch/core/models.py
dssketch/core/validation.py
dssketch/data/discrete-axis-labels.yaml
dssketch/data/font-resources-translations.json
dssketch/data/stylenames.json
dssketch/data/unified-mappings.json
dssketch/data/unified-mappings.yaml
dssketch/parsers/__init__.py
dssketch/parsers/dss_parser.py
dssketch/utils/__init__.py
dssketch/utils/conditions.py
dssketch/utils/discrete.py
dssketch/utils/dss_validator.py
dssketch/utils/logging.py
dssketch/utils/patterns.py
dssketch/writers/__init__.py
dssketch/writers/dss_writer.py
dssketch-1.1.8.dist-info/licenses/LICENSE
dssketch-1.1.8.dist-info/METADATA
dssketch-1.1.8.dist-info/WHEEL
dssketch-1.1.8.dist-info/entry_points.txt
dssketch-1.1.8.dist-info/top_level.txt
dssketch-1.1.8.dist-info/RECORD
