Metadata-Version: 2.4
Name: dssketch
Version: 1.1.8
Summary: Human-friendly alternative to DesignSpace XML - provides simple, intuitive text format for variable font design with 84-97% size reduction
Author-email: Alexander Lubovenko <lubovenko@gmail.com>
License-Expression: MIT
Project-URL: Homepage, https://github.com/typedev/dssketch
Project-URL: Documentation, https://github.com/typedev/dssketch#readme
Project-URL: Repository, https://github.com/typedev/dssketch.git
Project-URL: Issues, https://github.com/typedev/dssketch/issues
Keywords: fonts,designspace,variable-fonts,typography,font-design,ufo-fonts
Classifier: Development Status :: 4 - Beta
Classifier: Intended Audience :: Developers
Classifier: Topic :: Text Processing :: Fonts
Classifier: Programming Language :: Python :: 3
Classifier: Programming Language :: Python :: 3.8
Classifier: Programming Language :: Python :: 3.9
Classifier: Programming Language :: Python :: 3.10
Classifier: Programming Language :: Python :: 3.11
Classifier: Programming Language :: Python :: 3.12
Classifier: Operating System :: OS Independent
Requires-Python: >=3.8
License-File: LICENSE
Requires-Dist: fonttools>=4.38.0
Requires-Dist: defcon>=0.10.0
Requires-Dist: fontParts>=0.12.0
Requires-Dist: pyyaml>=6.0
Provides-Extra: dev
Requires-Dist: pytest>=7.0; extra == "dev"
Requires-Dist: pytest-cov>=4.0; extra == "dev"
Requires-Dist: black>=23.0; extra == "dev"
Requires-Dist: mypy>=1.0; extra == "dev"
Requires-Dist: ruff>=0.1.0; extra == "dev"
Dynamic: license-file
